xontrib/thefuck.py
xontrib_thefuck-0.3.6.dist-info/LICENSE.txt
xontrib_thefuck-0.3.6.dist-info/METADATA
xontrib_thefuck-0.3.6.dist-info/WHEEL
xontrib_thefuck-0.3.6.dist-info/top_level.txt
xontrib_thefuck-0.3.6.dist-info/RECORD
